MANIFEST.in
readme.txt
setup.cfg
setup.py
mongoqueue/__init__.py
mongoqueue/lock.py
mongoqueue/mongoqueue.py
mongoqueue/test.py
mongoqueue.egg-info/PKG-INFO
mongoqueue.egg-info/SOURCES.txt
mongoqueue.egg-info/dependency_links.txt
mongoqueue.egg-info/requires.txt
mongoqueue.egg-info/top_level.txt
mongoqueue.egg-info/zip-safe