Metadata-Version: 1.1
Name: mongoqueue
Version: 0.7.0
Summary: A queue using mongo as backend storage.
Home-page: http://pypi.python.org/pypi/mongoqueue
Author: Kapil Thangavelu
Author-email: kapil.foss@gmail.com
License: BSD-derived
Platform: UNKNOWN
Classifier: Intended Audience :: Developers
Classifier: Programming Language :: Python
Classifier: Operating System :: OS Independent
